[{"tagName":"script","voidTag":false,"meta":{"plugin":"html-webpack-plugin"},"attributes":{"defer":true,"src":"/js/chunk-vendors-legacy.3e733e03.js"}},{"tagName":"script","voidTag":false,"meta":{"plugin":"html-webpack-plugin"},"attributes":{"defer":true,"src":"/js/app-legacy.aa24dc5f.js"}},{"tagName":"link","voidTag":true,"meta":{"plugin":"html-webpack-plugin"},"attributes":{"href":"/css/chunk-vendors.562f0668.css","rel":"stylesheet"}},{"tagName":"link","voidTag":true,"meta":{"plugin":"html-webpack-plugin"},"attributes":{"href":"/css/app.ac573938.css","rel":"stylesheet"}}]